Metadata-Version: 1.0
Name: pysocketio
Version: 0.9.6a3
Summary: Socket.IO compatible server with Gevent support
Home-page: https://github.com/Smartupz/gevent-socketio
Author: Łukasz Rekucki
Author-email: lrekucki+socketio@gmail.com
License: UNKNOWN
Platform: UNKNOWN
Classifier: Development Status :: 4 - Beta
Classifier: Programming Language :: Python
Classifier: Topic :: Internet
Classifier: Topic :: Software Development :: Libraries :: Python Modules
Classifier: Intended Audience :: Developers
Classifier: Operating System :: POSIX
Classifier: Operating System :: MacOS :: MacOS X
Classifier: License :: OSI Approved :: BSD License
